watcherlab/__about__.py
watcherlab/__init__.py
watcherlab/enum.py
watcherlab/ti/__about__.py
watcherlab/ti/__init__.py
watcherlab/ti/common.py
watcherlab/ti/enum.py
watcherlab/ti/exception.py
watcherlab/ti/feed.py
watcherlab/ti/intelligence.py
watcherlab/ti/platform.py
watcherlab/ti/querier.py
watcherlab_ti_client_python-0.0.2.dist-info/LICENSE
watcherlab_ti_client_python-0.0.2.dist-info/METADATA
watcherlab_ti_client_python-0.0.2.dist-info/WHEEL
watcherlab_ti_client_python-0.0.2.dist-info/top_level.txt
watcherlab_ti_client_python-0.0.2.dist-info/RECORD
