Metadata-Version: 2.1
Name: watcherlab-ti-client-python
Version: 0.0.2
Summary: Watcherlab threat intelligence client
Home-page: https://github.com/watcherlab/ti-client-python
Author: watcherlab
Author-email: service@watcherlab.com
Project-URL: GitHub, https://github.com/watcherlab/ti-client-python
Project-URL: Gitee, https://gitee.com/beijing_watcherlab/ti-client-python/
Classifier: Development Status :: 3 - Alpha
Classifier: Natural Language :: Chinese (Simplified)
Classifier: Programming Language :: Python :: 3
Classifier: Programming Language :: Python :: 3.6
Classifier: License :: OSI Approved :: BSD License
Classifier: Operating System :: OS Independent
Requires-Python: >=3.6
License-File: LICENSE
